docs_with_docusarus/src/components/MDXContent.js
docs_with_docusarus/src/components/HomepageFeatures/index.tsx
docs_with_docusarus/src/components/HomepageFeatures/styles.module.css
docs_with_docusarus/src/components/VersionsArchived/index.tsx
docs_with_docusarus/src/components/VersionsArchived/styles.module.css
docs_with_docusarus/src/css/custom.css
docs_with_docusarus/src/pages/index.module.css
docs_with_docusarus/src/pages/index.tsx
docs_with_docusarus/src/pages/markdown-page.mdx
docs_with_docusarus/src/pages/versions.mdx
docs_with_docusarus/src/theme/NavbarItem/ComponentTypes.tsx
docs_with_docusarus/src/theme/NavbarItem/UnifiedVersionsDropdownNavbarItem/index.tsx
docs_with_docusarus/src/theme/NavbarItem/UnifiedVersionsDropdownNavbarItem/styles.module.css
src/__init__.py
test_python_uv_project_template-0.0.3.dist-info/METADATA
test_python_uv_project_template-0.0.3.dist-info/WHEEL
test_python_uv_project_template-0.0.3.dist-info/entry_points.txt
test_python_uv_project_template-0.0.3.dist-info/licenses/LICENSE
test_python_uv_project_template-0.0.3.dist-info/RECORD
