Metadata-Version: 2.4
Name: test-python-uv-project-template
Version: 0.0.3
Summary: 🐍 Just a template of Python project be managed by UV.
Project-URL: Homepage, https://github.com/Chisanan232/Template-Python-UV-Project
Project-URL: Repository, https://github.com/Chisanan232/Template-Python-UV-Project
Author-email: Chisanan232 <chi10211201@cycu.org.tw>
License: 
License-File: LICENSE
Classifier: Development Status :: 3 - Alpha
Classifier: Intended Audience :: Developers
Classifier: License :: OSI Approved :: MIT License
Classifier: Operating System :: OS Independent
Classifier: Programming Language :: Python :: 3
Classifier: Programming Language :: Python :: 3.12
Classifier: Programming Language :: Python :: 3.13
Classifier: Programming Language :: Python :: 3.14
Classifier: Topic :: Software Development :: Libraries :: Python Modules
Classifier: Topic :: Utilities
Requires-Python: <4.0,>=3.12
